{"version":"0.4","title":"front1","type":"page","content":[{"id":"6e57b0b9","settings":[],"elements":[{"id":"832a742","settings":{"_column_size":100},"elements":[{"id":"74613dd5","settings":{"editor":"<!-- wp:group -->\n<div class=\"wp-block-group\"><div class=\"wp-block-group__inner-container\"><!-- wp:group {\"backgroundColor\":\"accent-1\",\"textColor\":\"accent-2\"} -->\n<div class=\"wp-block-group has-accent-2-color has-accent-1-background-color has-text-color has-background\"><div class=\"wp-block-group__inner-container\"><!-- wp:group -->\n<div class=\"wp-block-group\"><div class=\"wp-block-group__inner-container\"><!-- wp:heading {\"textAlign\":\"center\"} -->\n<h2 class=\"has-text-align-center\"><strong>Ever got stuck about what to wear!! <\/strong><\/h2>\n<!-- \/wp:heading -->\n\n<!-- wp:heading {\"textAlign\":\"center\"} -->\n<h2 class=\"has-text-align-center\"><strong>or Started wondering will it be appropriate\u2026\u2026<\/strong><\/h2>\n<!-- \/wp:heading --><\/div><\/div>\n<!-- \/wp:group --><\/div><\/div>\n<!-- \/wp:group --><\/div><\/div>\n<!-- \/wp:group -->\n\n<!-- wp:paragraph -->\n<p><\/p>\n<!-- \/wp:paragraph -->"},"elements":[],"isInner":false,"widgetType":"text-editor","elType":"widget"}],"isInner":false,"elType":"column"}],"isInner":false,"elType":"section"}]}